polishstring/__init__.py
polishstring/polishstring.py
polishstring-0.0.2.dist-info/METADATA
polishstring-0.0.2.dist-info/WHEEL
polishstring-0.0.2.dist-info/top_level.txt
polishstring-0.0.2.dist-info/RECORD
