Metadata-Version: 2.1
Name: polishstring
Version: 0.0.2
Summary: Polishstring Interconversion
Home-page: UNKNOWN
Author: Tanmay Mandal
Author-email: tanmay.mandal@zohomail.in
License: MIT
Platform: UNKNOWN
Requires-Python: >=3.6
Requires-Dist: stringtokenizer
